yandex_metrika_logs_api/__init__.py
yandex_metrika_logs_api/client.py
yandex_metrika_logs_api/constants.py
yandex_metrika_logs_api/exceptions.py
yandex_metrika_logs_api/schemas/hits.py
yandex_metrika_logs_api/schemas/visits.py
yandex_metrika_logs_api-0.1.4.dist-info/LICENSE
yandex_metrika_logs_api-0.1.4.dist-info/METADATA
yandex_metrika_logs_api-0.1.4.dist-info/WHEEL
yandex_metrika_logs_api-0.1.4.dist-info/RECORD
